deeru_api/__init__.py
deeru_api/apps.py
deeru_api/consts.py
deeru_api/manager.py
deeru_api/response.py
deeru_api/urls.py
deeru_api/views.py
deeru_api-1.0.2.dist-info/METADATA
deeru_api-1.0.2.dist-info/RECORD
deeru_api-1.0.2.dist-info/WHEEL
deeru_api-1.0.2.dist-info/top_level.txt
